hyddown/__init__.py
hyddown/fire.py
hyddown/hdclass.py
hyddown/test_all.py
hyddown/thermesh.py
hyddown/transport.py
hyddown/validator.py
hyddown/examples/controlvalve.yml
hyddown/examples/cv_filling.yml
hyddown/examples/filling.yml
hyddown/examples/fillingH2.yml
hyddown/examples/input.yml
hyddown/examples/isenthalpic.yml
hyddown/examples/isentropic.yml
hyddown/examples/mdot_filling.yml
hyddown/examples/ng.yml
hyddown/examples/ng_inlet.yml
hyddown/examples/ng_outlet.yml
hyddown/examples/psv.yml
hyddown/examples/psv_sb.yml
hyddown/examples/relief.yml
hyddown/examples/scema_check.yml
hyddown-0.23.0.data/scripts/hyddown_main.py
hyddown-0.23.0.data/scripts/streamlit_app.py
hyddown-0.23.0.dist-info/LICENSE
hyddown-0.23.0.dist-info/METADATA
hyddown-0.23.0.dist-info/WHEEL
hyddown-0.23.0.dist-info/top_level.txt
hyddown-0.23.0.dist-info/RECORD
