Metadata-Version: 2.2
Name: HydDown
Version: 0.23.0
Summary: Hydrogen (or other pure gas phase species) pressure vessel filling and discharge calculations
Home-page: https://github.com/andr1976/HydDown/
Author: Anders Andreasen
Author-email: andr1976@gmail.com
Project-URL: Bug Tracker, https://github.com/andr1976/HydDown/new/main/issues
Classifier: Programming Language :: Python :: 3
Classifier: License :: OSI Approved :: MIT License
Classifier: Operating System :: OS Independent
Requires-Python: <3.12,>=3.6
License-File: LICENSE
Requires-Dist: tqdm
Requires-Dist: streamlit>=0.89
Requires-Dist: pandas>=1.1.4
Requires-Dist: matplotlib>=3.3.3
Requires-Dist: numpy>=1.19.5
Requires-Dist: pytest>=6.2.3
Requires-Dist: Cerberus>=1.3.3
Requires-Dist: CoolProp>=6.4.1
Requires-Dist: PyYAML>=5.4.1
Requires-Dist: scipy>=1.6.0
Requires-Dist: fluids
